pnomo/__init__.py
pnomo/lib.py
beta_beam-0.0.4.dist-info/METADATA
beta_beam-0.0.4.dist-info/WHEEL
beta_beam-0.0.4.dist-info/entry_points.txt
beta_beam-0.0.4.dist-info/license
beta_beam-0.0.4.dist-info/top_level.txt
beta_beam-0.0.4.dist-info/RECORD
