Metadata-Version: 2.1
Name: beta-beam
Version: 0.0.4
Summary: My last hope to get a degree...
Home-page: https://github.com/patod01/beta-beam
Author: Patricio C. V. - patod01
Author-email: patod01@telegmail.com
License: WTFPL
Platform: windous
Classifier: License :: Freeware
Classifier: Operating System :: Microsoft :: Windows :: Windows 10
Classifier: Programming Language :: Python :: 3.9
Requires-Python: >=3.9
